[
  {
    "timestamp": "2025-05-27T09:48:38.974Z",
    "messageType": "END_TURN",
    "stage": "after",
    "gameState": "{\"units\":[{\"id\":1,\"x\":1,\"y\":1,\"team\":\"player1\",\"hp\":20,\"atk\":8,\"def\":5,\"movementRange\":5,\"visionRange\":4,\"movementLeft\":5,\"hasAttacked\":false,\"name\":\"Anastasia\",\"sprite\":\"dist/sprites/(Archer) Anastasia (Summer)_portrait.webp\",\"skills\":[{\"id\":\"Mahalapraya\",\"onCooldownUntil\":0}],\"noblePhantasms\":[{\"id\":1,\"name\":\"Snegleta・Snegurochka: Summer Snow\",\"description\":\"Unleashes the power of summer\",\"cooldown\":5}],\"reactions\":[{\"id\":1,\"name\":\"Instinct\",\"description\":\"May evade incoming attacks\"}],\"combatSent\":{},\"combatReceived\":{},\"processedCombatSent\":[],\"processedCombatReceived\":[],\"canCounter\":false,\"counteringAgainstWho\":null},{\"id\":2,\"x\":3,\"y\":1,\"team\":\"player2\",\"hp\":18,\"atk\":6,\"def\":7,\"movementRange\":3,\"movementLeft\":3,\"hasAttacked\":false,\"name\":\"Artoria\",\"sprite\":\"dist/sprites/(Saber) Artoria_portrait.png\",\"skills\":[{\"id\":\"Mahalapraya\",\"onCooldownUntil\":0}],\"noblePhantasms\":[{\"id\":1,\"name\":\"Excalibur\",\"description\":\"Unleash holy sword energy\",\"cooldown\":5}],\"reactions\":[{\"id\":1,\"name\":\"Instinct\",\"description\":\"May evade incoming attacks\"}],\"combatSent\":[],\"combatReceived\":{},\"processedCombatSent\":[],\"processedCombatReceived\":[],\"canCounter\":false,\"counteringAgainstWho\":null,\"effects\":[],\"effectsReceived\":[],\"statusIfHit\":null,\"agilityChecks\":null,\"luckChecks\":null,\"baseAgility\":3,\"baseLuck\":18}],\"turn\":\"player2\",\"currentTurn\":2,\"currentRound\":1,\"turnsPerRound\":3,\"players\":{\"aedfeb71-120d-454b-9134-495644ad36af\":{\"id\":\"aedfeb71-120d-454b-9134-495644ad36af\",\"username\":\"a\",\"team\":\"player1\"},\"162d4d87-89a7-4017-a042-4f989237d609\":{\"id\":\"162d4d87-89a7-4017-a042-4f989237d609\",\"username\":\"b\",\"team\":\"player2\"}},\"detectionsThisTurn\":[],\"pendingCombatProcesses\":false}",
    "turn": 2,
    "round": 1
  },
  {
    "timestamp": "2025-05-27T09:48:40.345Z",
    "messageType": "END_TURN",
    "stage": "after",
    "gameState": "{\"units\":[{\"id\":1,\"x\":1,\"y\":1,\"team\":\"player1\",\"hp\":20,\"atk\":8,\"def\":5,\"movementRange\":5,\"visionRange\":4,\"movementLeft\":5,\"hasAttacked\":false,\"name\":\"Anastasia\",\"sprite\":\"dist/sprites/(Archer) Anastasia (Summer)_portrait.webp\",\"skills\":[{\"id\":\"Mahalapraya\",\"onCooldownUntil\":0}],\"noblePhantasms\":[{\"id\":1,\"name\":\"Snegleta・Snegurochka: Summer Snow\",\"description\":\"Unleashes the power of summer\",\"cooldown\":5}],\"reactions\":[{\"id\":1,\"name\":\"Instinct\",\"description\":\"May evade incoming attacks\"}],\"combatSent\":{},\"combatReceived\":{},\"processedCombatSent\":[],\"processedCombatReceived\":[],\"canCounter\":false,\"counteringAgainstWho\":null},{\"id\":2,\"x\":3,\"y\":1,\"team\":\"player2\",\"hp\":18,\"atk\":6,\"def\":7,\"movementRange\":3,\"movementLeft\":3,\"hasAttacked\":false,\"name\":\"Artoria\",\"sprite\":\"dist/sprites/(Saber) Artoria_portrait.png\",\"skills\":[{\"id\":\"Mahalapraya\",\"onCooldownUntil\":0}],\"noblePhantasms\":[{\"id\":1,\"name\":\"Excalibur\",\"description\":\"Unleash holy sword energy\",\"cooldown\":5}],\"reactions\":[{\"id\":1,\"name\":\"Instinct\",\"description\":\"May evade incoming attacks\"}],\"combatSent\":[],\"combatReceived\":{},\"processedCombatSent\":[],\"processedCombatReceived\":[],\"canCounter\":false,\"counteringAgainstWho\":null,\"effects\":[],\"effectsReceived\":[],\"statusIfHit\":null,\"agilityChecks\":null,\"luckChecks\":null,\"baseAgility\":3,\"baseLuck\":18}],\"turn\":\"player1\",\"currentTurn\":3,\"currentRound\":1,\"turnsPerRound\":3,\"players\":{\"aedfeb71-120d-454b-9134-495644ad36af\":{\"id\":\"aedfeb71-120d-454b-9134-495644ad36af\",\"username\":\"a\",\"team\":\"player1\"},\"162d4d87-89a7-4017-a042-4f989237d609\":{\"id\":\"162d4d87-89a7-4017-a042-4f989237d609\",\"username\":\"b\",\"team\":\"player2\"}},\"detectionsThisTurn\":[],\"pendingCombatProcesses\":false}",
    "turn": 3,
    "round": 1
  },
  {
    "timestamp": "2025-05-27T09:48:41.345Z",
    "messageType": "END_TURN",
    "stage": "after",
    "gameState": "{\"units\":[{\"id\":1,\"x\":1,\"y\":1,\"team\":\"player1\",\"hp\":20,\"atk\":8,\"def\":5,\"movementRange\":5,\"visionRange\":4,\"movementLeft\":5,\"hasAttacked\":false,\"name\":\"Anastasia\",\"sprite\":\"dist/sprites/(Archer) Anastasia (Summer)_portrait.webp\",\"skills\":[{\"id\":\"Mahalapraya\",\"onCooldownUntil\":0}],\"noblePhantasms\":[{\"id\":1,\"name\":\"Snegleta・Snegurochka: Summer Snow\",\"description\":\"Unleashes the power of summer\",\"cooldown\":5}],\"reactions\":[{\"id\":1,\"name\":\"Instinct\",\"description\":\"May evade incoming attacks\"}],\"combatSent\":{},\"combatReceived\":{},\"processedCombatSent\":[],\"processedCombatReceived\":[],\"canCounter\":false,\"counteringAgainstWho\":null},{\"id\":2,\"x\":3,\"y\":1,\"team\":\"player2\",\"hp\":18,\"atk\":6,\"def\":7,\"movementRange\":3,\"movementLeft\":3,\"hasAttacked\":false,\"name\":\"Artoria\",\"sprite\":\"dist/sprites/(Saber) Artoria_portrait.png\",\"skills\":[{\"id\":\"Mahalapraya\",\"onCooldownUntil\":0}],\"noblePhantasms\":[{\"id\":1,\"name\":\"Excalibur\",\"description\":\"Unleash holy sword energy\",\"cooldown\":5}],\"reactions\":[{\"id\":1,\"name\":\"Instinct\",\"description\":\"May evade incoming attacks\"}],\"combatSent\":[],\"combatReceived\":{},\"processedCombatSent\":[],\"processedCombatReceived\":[],\"canCounter\":false,\"counteringAgainstWho\":null,\"effects\":[],\"effectsReceived\":[],\"statusIfHit\":null,\"agilityChecks\":null,\"luckChecks\":null,\"baseAgility\":3,\"baseLuck\":18}],\"turn\":\"player2\",\"currentTurn\":4,\"currentRound\":2,\"turnsPerRound\":3,\"players\":{\"aedfeb71-120d-454b-9134-495644ad36af\":{\"id\":\"aedfeb71-120d-454b-9134-495644ad36af\",\"username\":\"a\",\"team\":\"player1\"},\"162d4d87-89a7-4017-a042-4f989237d609\":{\"id\":\"162d4d87-89a7-4017-a042-4f989237d609\",\"username\":\"b\",\"team\":\"player2\"}},\"detectionsThisTurn\":[],\"pendingCombatProcesses\":false}",
    "turn": 4,
    "round": 2
  },
  {
    "timestamp": "2025-05-27T09:48:42.763Z",
    "messageType": "END_TURN",
    "stage": "after",
    "gameState": "{\"units\":[{\"id\":1,\"x\":1,\"y\":1,\"team\":\"player1\",\"hp\":20,\"atk\":8,\"def\":5,\"movementRange\":5,\"visionRange\":4,\"movementLeft\":5,\"hasAttacked\":false,\"name\":\"Anastasia\",\"sprite\":\"dist/sprites/(Archer) Anastasia (Summer)_portrait.webp\",\"skills\":[{\"id\":\"Mahalapraya\",\"onCooldownUntil\":0}],\"noblePhantasms\":[{\"id\":1,\"name\":\"Snegleta・Snegurochka: Summer Snow\",\"description\":\"Unleashes the power of summer\",\"cooldown\":5}],\"reactions\":[{\"id\":1,\"name\":\"Instinct\",\"description\":\"May evade incoming attacks\"}],\"combatSent\":{},\"combatReceived\":{},\"processedCombatSent\":[],\"processedCombatReceived\":[],\"canCounter\":false,\"counteringAgainstWho\":null},{\"id\":2,\"x\":3,\"y\":1,\"team\":\"player2\",\"hp\":18,\"atk\":6,\"def\":7,\"movementRange\":3,\"movementLeft\":3,\"hasAttacked\":false,\"name\":\"Artoria\",\"sprite\":\"dist/sprites/(Saber) Artoria_portrait.png\",\"skills\":[{\"id\":\"Mahalapraya\",\"onCooldownUntil\":0}],\"noblePhantasms\":[{\"id\":1,\"name\":\"Excalibur\",\"description\":\"Unleash holy sword energy\",\"cooldown\":5}],\"reactions\":[{\"id\":1,\"name\":\"Instinct\",\"description\":\"May evade incoming attacks\"}],\"combatSent\":[],\"combatReceived\":{},\"processedCombatSent\":[],\"processedCombatReceived\":[],\"canCounter\":false,\"counteringAgainstWho\":null,\"effects\":[],\"effectsReceived\":[],\"statusIfHit\":null,\"agilityChecks\":null,\"luckChecks\":null,\"baseAgility\":3,\"baseLuck\":18}],\"turn\":\"player1\",\"currentTurn\":5,\"currentRound\":2,\"turnsPerRound\":3,\"players\":{\"aedfeb71-120d-454b-9134-495644ad36af\":{\"id\":\"aedfeb71-120d-454b-9134-495644ad36af\",\"username\":\"a\",\"team\":\"player1\"},\"162d4d87-89a7-4017-a042-4f989237d609\":{\"id\":\"162d4d87-89a7-4017-a042-4f989237d609\",\"username\":\"b\",\"team\":\"player2\"}},\"detectionsThisTurn\":[],\"pendingCombatProcesses\":false}",
    "turn": 5,
    "round": 2
  },
  {
    "timestamp": "2025-05-27T09:48:45.669Z",
    "messageType": "MOVE_UNIT",
    "stage": "after",
    "gameState": "{\"units\":[{\"id\":1,\"x\":2,\"y\":2,\"team\":\"player1\",\"hp\":20,\"atk\":8,\"def\":5,\"movementRange\":5,\"visionRange\":4,\"movementLeft\":3,\"hasAttacked\":false,\"name\":\"Anastasia\",\"sprite\":\"dist/sprites/(Archer) Anastasia (Summer)_portrait.webp\",\"skills\":[{\"id\":\"Mahalapraya\",\"onCooldownUntil\":0}],\"noblePhantasms\":[{\"id\":1,\"name\":\"Snegleta・Snegurochka: Summer Snow\",\"description\":\"Unleashes the power of summer\",\"cooldown\":5}],\"reactions\":[{\"id\":1,\"name\":\"Instinct\",\"description\":\"May evade incoming attacks\"}],\"combatSent\":{},\"combatReceived\":{},\"processedCombatSent\":[],\"processedCombatReceived\":[],\"canCounter\":false,\"counteringAgainstWho\":null},{\"id\":2,\"x\":3,\"y\":1,\"team\":\"player2\",\"hp\":18,\"atk\":6,\"def\":7,\"movementRange\":3,\"movementLeft\":3,\"hasAttacked\":false,\"name\":\"Artoria\",\"sprite\":\"dist/sprites/(Saber) Artoria_portrait.png\",\"skills\":[{\"id\":\"Mahalapraya\",\"onCooldownUntil\":0}],\"noblePhantasms\":[{\"id\":1,\"name\":\"Excalibur\",\"description\":\"Unleash holy sword energy\",\"cooldown\":5}],\"reactions\":[{\"id\":1,\"name\":\"Instinct\",\"description\":\"May evade incoming attacks\"}],\"combatSent\":[],\"combatReceived\":{},\"processedCombatSent\":[],\"processedCombatReceived\":[],\"canCounter\":false,\"counteringAgainstWho\":null,\"effects\":[],\"effectsReceived\":[],\"statusIfHit\":null,\"agilityChecks\":null,\"luckChecks\":null,\"baseAgility\":3,\"baseLuck\":18}],\"turn\":\"player1\",\"currentTurn\":5,\"currentRound\":2,\"turnsPerRound\":3,\"players\":{\"aedfeb71-120d-454b-9134-495644ad36af\":{\"id\":\"aedfeb71-120d-454b-9134-495644ad36af\",\"username\":\"a\",\"team\":\"player1\"},\"162d4d87-89a7-4017-a042-4f989237d609\":{\"id\":\"162d4d87-89a7-4017-a042-4f989237d609\",\"username\":\"b\",\"team\":\"player2\"}},\"detectionsThisTurn\":[],\"pendingCombatProcesses\":false}",
    "turn": 5,
    "round": 2
  },
  {
    "timestamp": "2025-05-27T09:48:46.825Z",
    "messageType": "END_TURN",
    "stage": "after",
    "gameState": "{\"units\":[{\"id\":1,\"x\":2,\"y\":2,\"team\":\"player1\",\"hp\":20,\"atk\":8,\"def\":5,\"movementRange\":5,\"visionRange\":4,\"movementLeft\":5,\"hasAttacked\":false,\"name\":\"Anastasia\",\"sprite\":\"dist/sprites/(Archer) Anastasia (Summer)_portrait.webp\",\"skills\":[{\"id\":\"Mahalapraya\",\"onCooldownUntil\":0}],\"noblePhantasms\":[{\"id\":1,\"name\":\"Snegleta・Snegurochka: Summer Snow\",\"description\":\"Unleashes the power of summer\",\"cooldown\":5}],\"reactions\":[{\"id\":1,\"name\":\"Instinct\",\"description\":\"May evade incoming attacks\"}],\"combatSent\":{},\"combatReceived\":{},\"processedCombatSent\":[],\"processedCombatReceived\":[],\"canCounter\":false,\"counteringAgainstWho\":null},{\"id\":2,\"x\":3,\"y\":1,\"team\":\"player2\",\"hp\":18,\"atk\":6,\"def\":7,\"movementRange\":3,\"movementLeft\":3,\"hasAttacked\":false,\"name\":\"Artoria\",\"sprite\":\"dist/sprites/(Saber) Artoria_portrait.png\",\"skills\":[{\"id\":\"Mahalapraya\",\"onCooldownUntil\":0}],\"noblePhantasms\":[{\"id\":1,\"name\":\"Excalibur\",\"description\":\"Unleash holy sword energy\",\"cooldown\":5}],\"reactions\":[{\"id\":1,\"name\":\"Instinct\",\"description\":\"May evade incoming attacks\"}],\"combatSent\":[],\"combatReceived\":{},\"processedCombatSent\":[],\"processedCombatReceived\":[],\"canCounter\":false,\"counteringAgainstWho\":null,\"effects\":[],\"effectsReceived\":[],\"statusIfHit\":null,\"agilityChecks\":null,\"luckChecks\":null,\"baseAgility\":3,\"baseLuck\":18}],\"turn\":\"player2\",\"currentTurn\":6,\"currentRound\":2,\"turnsPerRound\":3,\"players\":{\"aedfeb71-120d-454b-9134-495644ad36af\":{\"id\":\"aedfeb71-120d-454b-9134-495644ad36af\",\"username\":\"a\",\"team\":\"player1\"},\"162d4d87-89a7-4017-a042-4f989237d609\":{\"id\":\"162d4d87-89a7-4017-a042-4f989237d609\",\"username\":\"b\",\"team\":\"player2\"}},\"detectionsThisTurn\":[],\"pendingCombatProcesses\":false}",
    "turn": 6,
    "round": 2
  },
  {
    "timestamp": "2025-05-27T09:48:49.854Z",
    "messageType": "MOVE_UNIT",
    "stage": "after",
    "gameState": "{\"units\":[{\"id\":1,\"x\":2,\"y\":2,\"team\":\"player1\",\"hp\":20,\"atk\":8,\"def\":5,\"movementRange\":5,\"visionRange\":4,\"movementLeft\":5,\"hasAttacked\":false,\"name\":\"Anastasia\",\"sprite\":\"dist/sprites/(Archer) Anastasia (Summer)_portrait.webp\",\"skills\":[{\"id\":\"Mahalapraya\",\"onCooldownUntil\":0}],\"noblePhantasms\":[{\"id\":1,\"name\":\"Snegleta・Snegurochka: Summer Snow\",\"description\":\"Unleashes the power of summer\",\"cooldown\":5}],\"reactions\":[{\"id\":1,\"name\":\"Instinct\",\"description\":\"May evade incoming attacks\"}],\"combatSent\":{},\"combatReceived\":{},\"processedCombatSent\":[],\"processedCombatReceived\":[],\"canCounter\":false,\"counteringAgainstWho\":null},{\"id\":2,\"x\":5,\"y\":1,\"team\":\"player2\",\"hp\":18,\"atk\":6,\"def\":7,\"movementRange\":3,\"movementLeft\":1,\"hasAttacked\":false,\"name\":\"Artoria\",\"sprite\":\"dist/sprites/(Saber) Artoria_portrait.png\",\"skills\":[{\"id\":\"Mahalapraya\",\"onCooldownUntil\":0}],\"noblePhantasms\":[{\"id\":1,\"name\":\"Excalibur\",\"description\":\"Unleash holy sword energy\",\"cooldown\":5}],\"reactions\":[{\"id\":1,\"name\":\"Instinct\",\"description\":\"May evade incoming attacks\"}],\"combatSent\":[],\"combatReceived\":{},\"processedCombatSent\":[],\"processedCombatReceived\":[],\"canCounter\":false,\"counteringAgainstWho\":null,\"effects\":[],\"effectsReceived\":[],\"statusIfHit\":null,\"agilityChecks\":null,\"luckChecks\":null,\"baseAgility\":3,\"baseLuck\":18}],\"turn\":\"player2\",\"currentTurn\":6,\"currentRound\":2,\"turnsPerRound\":3,\"players\":{\"aedfeb71-120d-454b-9134-495644ad36af\":{\"id\":\"aedfeb71-120d-454b-9134-495644ad36af\",\"username\":\"a\",\"team\":\"player1\"},\"162d4d87-89a7-4017-a042-4f989237d609\":{\"id\":\"162d4d87-89a7-4017-a042-4f989237d609\",\"username\":\"b\",\"team\":\"player2\"}},\"detectionsThisTurn\":[],\"pendingCombatProcesses\":false}",
    "turn": 6,
    "round": 2
  },
  {
    "timestamp": "2025-05-27T09:48:50.569Z",
    "messageType": "END_TURN",
    "stage": "after",
    "gameState": "{\"units\":[{\"id\":1,\"x\":2,\"y\":2,\"team\":\"player1\",\"hp\":20,\"atk\":8,\"def\":5,\"movementRange\":5,\"visionRange\":4,\"movementLeft\":5,\"hasAttacked\":false,\"name\":\"Anastasia\",\"sprite\":\"dist/sprites/(Archer) Anastasia (Summer)_portrait.webp\",\"skills\":[{\"id\":\"Mahalapraya\",\"onCooldownUntil\":0}],\"noblePhantasms\":[{\"id\":1,\"name\":\"Snegleta・Snegurochka: Summer Snow\",\"description\":\"Unleashes the power of summer\",\"cooldown\":5}],\"reactions\":[{\"id\":1,\"name\":\"Instinct\",\"description\":\"May evade incoming attacks\"}],\"combatSent\":{},\"combatReceived\":{},\"processedCombatSent\":[],\"processedCombatReceived\":[],\"canCounter\":false,\"counteringAgainstWho\":null},{\"id\":2,\"x\":5,\"y\":1,\"team\":\"player2\",\"hp\":18,\"atk\":6,\"def\":7,\"movementRange\":3,\"movementLeft\":3,\"hasAttacked\":false,\"name\":\"Artoria\",\"sprite\":\"dist/sprites/(Saber) Artoria_portrait.png\",\"skills\":[{\"id\":\"Mahalapraya\",\"onCooldownUntil\":0}],\"noblePhantasms\":[{\"id\":1,\"name\":\"Excalibur\",\"description\":\"Unleash holy sword energy\",\"cooldown\":5}],\"reactions\":[{\"id\":1,\"name\":\"Instinct\",\"description\":\"May evade incoming attacks\"}],\"combatSent\":[],\"combatReceived\":{},\"processedCombatSent\":[],\"processedCombatReceived\":[],\"canCounter\":false,\"counteringAgainstWho\":null,\"effects\":[],\"effectsReceived\":[],\"statusIfHit\":null,\"agilityChecks\":null,\"luckChecks\":null,\"baseAgility\":3,\"baseLuck\":18}],\"turn\":\"player1\",\"currentTurn\":7,\"currentRound\":3,\"turnsPerRound\":3,\"players\":{\"aedfeb71-120d-454b-9134-495644ad36af\":{\"id\":\"aedfeb71-120d-454b-9134-495644ad36af\",\"username\":\"a\",\"team\":\"player1\"},\"162d4d87-89a7-4017-a042-4f989237d609\":{\"id\":\"162d4d87-89a7-4017-a042-4f989237d609\",\"username\":\"b\",\"team\":\"player2\"}},\"detectionsThisTurn\":[],\"pendingCombatProcesses\":false}",
    "turn": 7,
    "round": 3
  },
  {
    "timestamp": "2025-05-27T09:48:51.903Z",
    "messageType": "END_TURN",
    "stage": "after",
    "gameState": "{\"units\":[{\"id\":1,\"x\":2,\"y\":2,\"team\":\"player1\",\"hp\":20,\"atk\":8,\"def\":5,\"movementRange\":5,\"visionRange\":4,\"movementLeft\":5,\"hasAttacked\":false,\"name\":\"Anastasia\",\"sprite\":\"dist/sprites/(Archer) Anastasia (Summer)_portrait.webp\",\"skills\":[{\"id\":\"Mahalapraya\",\"onCooldownUntil\":0}],\"noblePhantasms\":[{\"id\":1,\"name\":\"Snegleta・Snegurochka: Summer Snow\",\"description\":\"Unleashes the power of summer\",\"cooldown\":5}],\"reactions\":[{\"id\":1,\"name\":\"Instinct\",\"description\":\"May evade incoming attacks\"}],\"combatSent\":{},\"combatReceived\":{},\"processedCombatSent\":[],\"processedCombatReceived\":[],\"canCounter\":false,\"counteringAgainstWho\":null},{\"id\":2,\"x\":5,\"y\":1,\"team\":\"player2\",\"hp\":18,\"atk\":6,\"def\":7,\"movementRange\":3,\"movementLeft\":3,\"hasAttacked\":false,\"name\":\"Artoria\",\"sprite\":\"dist/sprites/(Saber) Artoria_portrait.png\",\"skills\":[{\"id\":\"Mahalapraya\",\"onCooldownUntil\":0}],\"noblePhantasms\":[{\"id\":1,\"name\":\"Excalibur\",\"description\":\"Unleash holy sword energy\",\"cooldown\":5}],\"reactions\":[{\"id\":1,\"name\":\"Instinct\",\"description\":\"May evade incoming attacks\"}],\"combatSent\":[],\"combatReceived\":{},\"processedCombatSent\":[],\"processedCombatReceived\":[],\"canCounter\":false,\"counteringAgainstWho\":null,\"effects\":[],\"effectsReceived\":[],\"statusIfHit\":null,\"agilityChecks\":null,\"luckChecks\":null,\"baseAgility\":3,\"baseLuck\":18}],\"turn\":\"player2\",\"currentTurn\":8,\"currentRound\":3,\"turnsPerRound\":3,\"players\":{\"aedfeb71-120d-454b-9134-495644ad36af\":{\"id\":\"aedfeb71-120d-454b-9134-495644ad36af\",\"username\":\"a\",\"team\":\"player1\"},\"162d4d87-89a7-4017-a042-4f989237d609\":{\"id\":\"162d4d87-89a7-4017-a042-4f989237d609\",\"username\":\"b\",\"team\":\"player2\"}},\"detectionsThisTurn\":[],\"pendingCombatProcesses\":false}",
    "turn": 8,
    "round": 3
  },
  {
    "timestamp": "2025-05-27T09:48:53.545Z",
    "messageType": "END_TURN",
    "stage": "after",
    "gameState": "{\"units\":[{\"id\":1,\"x\":2,\"y\":2,\"team\":\"player1\",\"hp\":20,\"atk\":8,\"def\":5,\"movementRange\":5,\"visionRange\":4,\"movementLeft\":5,\"hasAttacked\":false,\"name\":\"Anastasia\",\"sprite\":\"dist/sprites/(Archer) Anastasia (Summer)_portrait.webp\",\"skills\":[{\"id\":\"Mahalapraya\",\"onCooldownUntil\":0}],\"noblePhantasms\":[{\"id\":1,\"name\":\"Snegleta・Snegurochka: Summer Snow\",\"description\":\"Unleashes the power of summer\",\"cooldown\":5}],\"reactions\":[{\"id\":1,\"name\":\"Instinct\",\"description\":\"May evade incoming attacks\"}],\"combatSent\":{},\"combatReceived\":{},\"processedCombatSent\":[],\"processedCombatReceived\":[],\"canCounter\":false,\"counteringAgainstWho\":null},{\"id\":2,\"x\":5,\"y\":1,\"team\":\"player2\",\"hp\":18,\"atk\":6,\"def\":7,\"movementRange\":3,\"movementLeft\":3,\"hasAttacked\":false,\"name\":\"Artoria\",\"sprite\":\"dist/sprites/(Saber) Artoria_portrait.png\",\"skills\":[{\"id\":\"Mahalapraya\",\"onCooldownUntil\":0}],\"noblePhantasms\":[{\"id\":1,\"name\":\"Excalibur\",\"description\":\"Unleash holy sword energy\",\"cooldown\":5}],\"reactions\":[{\"id\":1,\"name\":\"Instinct\",\"description\":\"May evade incoming attacks\"}],\"combatSent\":[],\"combatReceived\":{},\"processedCombatSent\":[],\"processedCombatReceived\":[],\"canCounter\":false,\"counteringAgainstWho\":null,\"effects\":[],\"effectsReceived\":[],\"statusIfHit\":null,\"agilityChecks\":null,\"luckChecks\":null,\"baseAgility\":3,\"baseLuck\":18}],\"turn\":\"player1\",\"currentTurn\":9,\"currentRound\":3,\"turnsPerRound\":3,\"players\":{\"aedfeb71-120d-454b-9134-495644ad36af\":{\"id\":\"aedfeb71-120d-454b-9134-495644ad36af\",\"username\":\"a\",\"team\":\"player1\"},\"162d4d87-89a7-4017-a042-4f989237d609\":{\"id\":\"162d4d87-89a7-4017-a042-4f989237d609\",\"username\":\"b\",\"team\":\"player2\"}},\"detectionsThisTurn\":[],\"pendingCombatProcesses\":false}",
    "turn": 9,
    "round": 3
  }
]